Py_search_address/__init__.py
Py_search_address/py_search_address.py
Py_search_address/search_address.py
Py_SearchAddress-0.0.1.dist-info/METADATA
Py_SearchAddress-0.0.1.dist-info/WHEEL
Py_SearchAddress-0.0.1.dist-info/top_level.txt
Py_SearchAddress-0.0.1.dist-info/RECORD
