Metadata-Version: 2.1
Name: Py-SearchAddress
Version: 0.0.1
Summary: UNKNOWN
Home-page: https://www.linkedin.com/in/felipe-macedo-de-oliveira-14a557185/
Author: Felipe Oliveira
Author-email: feoli.jobs@gmail.com
License: MIT
Keywords: Busca endereço,Search Address
Platform: UNKNOWN
Classifier: Development Status :: 4 - Beta
Classifier: Intended Audience :: Developers
Classifier: Topic :: Education :: Testing
Classifier: License :: OSI Approved :: MIT License
Classifier: Programming Language :: Python :: 3
Classifier: Programming Language :: Python :: 3.2
Classifier: Programming Language :: Python :: 3.3
Classifier: Programming Language :: Python :: 3.4
Requires-Dist: sh (>=1.11)
